{
    "technology": [
        {
            "name": "Wired",
            "url": "https://www.wired.com/feed/rss"
        }
    ],
    "entertainment": [
        {
            "name": "Variety",
            "url": "https://variety.com/feed/"
        },
        {
            "name": "Rolling Stone",
            "url": "https://www.rollingstone.com/music/music-news/feed/"
        }
    ],
    "environment": [
        {
            "name": "National Geographic",
            "url": "https://www.nationalgeographic.com/content/nationalgeographic/en_us/rss/index.rss"
        },
        {
            "name": "Nature News",
            "url": "https://www.nature.com/nature.rss"
        }
    ],
    "gaming": [
        {
            "name": "IGN",
            "url": "https://www.ign.com/rss/articles/feed"
        }
    ],
    "news": [
        {
            "name": "Asianet News",
            "url": "https://www.asianetnews.com/rss"
        },
        {
            "name": "Mathrubhumi News",
            "url": "https://sitemap.mpp.atexcloud.io/sitemaps/rss"
        }
    ]
}
